osl/__init__.py
osl/glm/README.md
osl/glm/__init__.py
osl/glm/glm_base.py
osl/glm/glm_epochs.py
osl/glm/glm_spectrum.py
osl/maxfilter/README.md
osl/maxfilter/__init__.py
osl/maxfilter/maxfilter.py
osl/preprocessing/README.md
osl/preprocessing/__init__.py
osl/preprocessing/batch.py
osl/preprocessing/ica_label.py
osl/preprocessing/mne_wrappers.py
osl/preprocessing/osl_wrappers.py
osl/preprocessing/plot_ica.py
osl/preprocessing/scratch.py
osl/report/README.md
osl/report/__init__.py
osl/report/preproc_report.py
osl/report/src_report.py
osl/report/templates/raw_subject_panel.html
osl/report/templates/raw_summary_panel.html
osl/report/templates/src_subject_panel.html
osl/report/templates/src_summary_panel.html
osl/report/templates/subject_report.html
osl/report/templates/summary_report.html
osl/source_recon/README.md
osl/source_recon/__init__.py
osl/source_recon/batch.py
osl/source_recon/beamforming.py
osl/source_recon/sign_flipping.py
osl/source_recon/wrappers.py
osl/source_recon/parcellation/__init__.py
osl/source_recon/parcellation/nii.py
osl/source_recon/parcellation/parcellation.py
osl/source_recon/parcellation/files/Glasser50_space-MNI152NLin6_res-8x8x8.nii.gz
osl/source_recon/parcellation/files/Glasser52_binary_space-MNI152NLin6_res-8x8x8.nii.gz
osl/source_recon/parcellation/files/HarvOxf-sub-Schaefer100-combined-2mm.nii.gz
osl/source_recon/parcellation/files/HarvOxf-sub-Schaefer100-combined-2mm_4d.nii.gz
osl/source_recon/parcellation/files/HarvOxf-sub-Schaefer100-combined-2mm_4d_ds8.nii.gz
osl/source_recon/parcellation/files/HarvardOxford-sub-prob-bin-2mm.nii.gz
osl/source_recon/parcellation/files/MNI152_T1_2mm_brain.nii.gz
osl/source_recon/parcellation/files/MNI152_T1_8mm_brain.nii.gz
osl/source_recon/parcellation/files/Schaefer2018_100Parcels_7Networks_order_FSLMNI152_2mm.nii.gz
osl/source_recon/parcellation/files/Schaefer2018_100Parcels_7Networks_order_FSLMNI152_2mm_4d.nii.gz
osl-1.1.0.dist-info/LICENSE
osl-1.1.0.dist-info/METADATA
osl-1.1.0.dist-info/WHEEL
osl-1.1.0.dist-info/entry_points.txt
osl-1.1.0.dist-info/top_level.txt
osl-1.1.0.dist-info/RECORD
